libelle/__init__.py
libelle/placeholder.py
libelle-0.0.1.dist-info/METADATA
libelle-0.0.1.dist-info/WHEEL
libelle-0.0.1.dist-info/entry_points.txt
libelle-0.0.1.dist-info/top_level.txt
libelle-0.0.1.dist-info/RECORD
